README.md
setup.py
kpages/__init__.py
kpages/api2doc.py
kpages/app.py
kpages/cache.py
kpages/consistenthash.py
kpages/context.py
kpages/kpages_init.py
kpages/kpages_rpc.py
kpages/kpages_service.py
kpages/kpages_tool.py
kpages/kpages_web.py
kpages/log.py
kpages/mongo_util.py
kpages/router.py
kpages/service.py
kpages/settings.py
kpages/utest.py
kpages/utility.py
kpages/web.py
kpages/web.zip
kpages.egg-info/PKG-INFO
kpages.egg-info/SOURCES.txt
kpages.egg-info/dependency_links.txt
kpages.egg-info/requires.txt
kpages.egg-info/top_level.txt